LICENSE
MANIFEST.in
README.md
setup.py
dawupxlrgo/__init__.py
dawupxlrgo/api_helper.py
dawupxlrgo/configuration.py
dawupxlrgo/dawupxlrgo_client.py
dawupxlrgo/decorators.py
dawupxlrgo.egg-info/PKG-INFO
dawupxlrgo.egg-info/SOURCES.txt
dawupxlrgo.egg-info/dependency_links.txt
dawupxlrgo.egg-info/requires.txt
dawupxlrgo.egg-info/top_level.txt
dawupxlrgo/controllers/__init__.py
dawupxlrgo/controllers/api_controller.py
dawupxlrgo/controllers/base_controller.py
dawupxlrgo/exceptions/__init__.py
dawupxlrgo/exceptions/api_exception.py
dawupxlrgo/http/__init__.py
dawupxlrgo/http/http_call_back.py
dawupxlrgo/http/http_client.py
dawupxlrgo/http/http_context.py
dawupxlrgo/http/http_method_enum.py
dawupxlrgo/http/http_request.py
dawupxlrgo/http/http_response.py
dawupxlrgo/http/requests_client.py
dawupxlrgo/http/auth/__init__.py
dawupxlrgo/http/auth/basic_auth.py
dawupxlrgo/models/__init__.py
dawupxlrgo/models/suite_code_enum.py
tests/__init__.py
tests/http_response_catcher.py
tests/test_helper.py
tests/controllers/__init__.py
tests/controllers/controller_test_base.py
tests/controllers/test_api_controller.py